{
	"swimmers": [
		{
			"lane":1,
			"school":"ISKL",
			"name":"KEVIN DAVIDSON",
			"time":""
		},
		{
			"lane":2,
			"school":"ISKL",
			"name":"DANIAL FAUZI",
			"time":""
		},
		{
			"lane":3,
			"school":"SAS",
			"name":"KEI HYOGO",
			"time":""
		},
		{
			"lane":4,
			"school":"TAS",
			"name":"IAN SILVERSTEIN",
			"time":""
		},
		{
			"lane":5,
			"school":"ISB",
			"name":"JONNIE BATCHELOR",
			"time":""
		},
		{
			"lane":6,
			"school":"JIS",
			"name":"CHRISTOPHER SIMPSON",
			"time":""
		},
		{
			"lane":7,
			"school":"JIS",
			"name":"JAKE SHORT",
			"time":""
		},
		{
			"lane":8,
			"school":"JIS",
			"name":"JAKE SHORT",
			"time":"121"
		}
	],
	"race_headings": {
		"title": "Boys 200M Freestyle",
		"match": "Heat 1",
		"length": "25"
	}

}